iqcampy/__init__.py
iqcampy/_modidx.py
iqcampy/core.py
iqcampy/storage.py
iqcampy-0.0.5.dist-info/LICENSE
iqcampy-0.0.5.dist-info/METADATA
iqcampy-0.0.5.dist-info/WHEEL
iqcampy-0.0.5.dist-info/entry_points.txt
iqcampy-0.0.5.dist-info/top_level.txt
iqcampy-0.0.5.dist-info/RECORD
