Metadata-Version: 2.1
Name: iqcampy
Version: 0.0.5
Summary: Read and visualize Specim IQcam hyperspectral images
Home-page: https://github.com/fligt/iqcampy
Author: Frank Ligterink
Author-email: frank.ligterink@gmail.nl
License: GNU General Public License v3
Keywords: hyperspectral-imaging Specim-IQ-Camera
Classifier: Development Status :: 4 - Beta
Classifier: Intended Audience :: Developers
Classifier: Natural Language :: English
Classifier: Programming Language :: Python :: 3.7
Classifier: Programming Language :: Python :: 3.8
Classifier: Programming Language :: Python :: 3.9
Classifier: Programming Language :: Python :: 3.10
Classifier: License :: OSI Approved :: GNU General Public License v3 (GPLv3)
Requires-Python: >=3.7
License-File: LICENSE
Requires-Dist: requests
Requires-Dist: tqdm
Requires-Dist: treelib
Requires-Dist: pathlib
Requires-Dist: numpy
Requires-Dist: matplotlib
Provides-Extra: dev
